octavia_tempest_plugin/__init__.py
octavia_tempest_plugin/config.py
octavia_tempest_plugin/opts.py
octavia_tempest_plugin/plugin.py
octavia_tempest_plugin/version.py
octavia_tempest_plugin/common/__init__.py
octavia_tempest_plugin/common/barbican_client_mgr.py
octavia_tempest_plugin/common/cert_utils.py
octavia_tempest_plugin/common/constants.py
octavia_tempest_plugin/common/decorators.py
octavia_tempest_plugin/common/requests_adapters.py
octavia_tempest_plugin/contrib/__init__.py
octavia_tempest_plugin/contrib/test_server/README.rst
octavia_tempest_plugin/contrib/test_server/__init__.py
octavia_tempest_plugin/contrib/test_server/test_server.go
octavia_tempest_plugin/hacking/__init__.py
octavia_tempest_plugin/hacking/checks.py
octavia_tempest_plugin/services/__init__.py
octavia_tempest_plugin/services/load_balancer/__init__.py
octavia_tempest_plugin/services/load_balancer/v2/__init__.py
octavia_tempest_plugin/services/load_balancer/v2/amphora_client.py
octavia_tempest_plugin/services/load_balancer/v2/availability_zone_capabilities_client.py
octavia_tempest_plugin/services/load_balancer/v2/availability_zone_client.py
octavia_tempest_plugin/services/load_balancer/v2/availability_zone_profile_client.py
octavia_tempest_plugin/services/load_balancer/v2/base_client.py
octavia_tempest_plugin/services/load_balancer/v2/flavor_capabilities_client.py
octavia_tempest_plugin/services/load_balancer/v2/flavor_client.py
octavia_tempest_plugin/services/load_balancer/v2/flavor_profile_client.py
octavia_tempest_plugin/services/load_balancer/v2/healthmonitor_client.py
octavia_tempest_plugin/services/load_balancer/v2/l7policy_client.py
octavia_tempest_plugin/services/load_balancer/v2/l7rule_client.py
octavia_tempest_plugin/services/load_balancer/v2/listener_client.py
octavia_tempest_plugin/services/load_balancer/v2/loadbalancer_client.py
octavia_tempest_plugin/services/load_balancer/v2/member_client.py
octavia_tempest_plugin/services/load_balancer/v2/pool_client.py
octavia_tempest_plugin-3.2.0.dist-info/AUTHORS
octavia_tempest_plugin-3.2.0.dist-info/LICENSE
octavia_tempest_plugin-3.2.0.dist-info/METADATA
octavia_tempest_plugin-3.2.0.dist-info/WHEEL
octavia_tempest_plugin-3.2.0.dist-info/entry_points.txt
octavia_tempest_plugin-3.2.0.dist-info/pbr.json
octavia_tempest_plugin-3.2.0.dist-info/top_level.txt
octavia_tempest_plugin-3.2.0.dist-info/RECORD
