Metadata-Version: 2.1
Name: octavia-tempest-plugin
Version: 3.2.0
Summary: Tempest plugin for Octavia
Home-page: https://docs.openstack.org/octavia-tempest-plugin/latest/
Author: OpenStack
Author-email: openstack-discuss@lists.openstack.org
Classifier: Environment :: OpenStack
Classifier: Intended Audience :: Information Technology
Classifier: Intended Audience :: System Administrators
Classifier: License :: OSI Approved :: Apache Software License
Classifier: Operating System :: POSIX :: Linux
Classifier: Programming Language :: Python
Classifier: Programming Language :: Python :: Implementation :: CPython
Classifier: Programming Language :: Python :: 3 :: Only
Classifier: Programming Language :: Python :: 3
Classifier: Programming Language :: Python :: 3.9
Classifier: Programming Language :: Python :: 3.10
Classifier: Programming Language :: Python :: 3.11
Classifier: Programming Language :: Python :: 3.12
Requires-Python: >=3.9
License-File: LICENSE
License-File: AUTHORS
Requires-Dist: cryptography >=3.0
Requires-Dist: python-dateutil >=2.5.3
Requires-Dist: pbr !=2.1.0,>=2.0.0
Requires-Dist: oslo.config >=5.2.0
Requires-Dist: oslo.log >=3.36.0
Requires-Dist: oslo.serialization !=2.19.1,>=2.18.0
Requires-Dist: oslo.utils >=3.33.0
Requires-Dist: oslotest >=3.2.0
Requires-Dist: python-barbicanclient >=4.5.2
Requires-Dist: pyOpenSSL >=17.1.0
Requires-Dist: requests >=2.14.2
Requires-Dist: tempest >=17.1.0
Requires-Dist: tenacity >=4.4.0
Requires-Dist: testtools >=2.2.0
Requires-Dist: keystoneauth1 >=3.3.0
Requires-Dist: httpx[http2] >=0.14.2
